{
    "enabled": true,
    "neededInstalledMods": [],
    "neededUninstalledMods": [],
    "spawns": [
        {
            "id": "fraxure-1",
            "pokemon": "fraxure",
            "presets": [
                "natural",
                "wild"
            ],
            "type": "pokemon",
            "spawnablePositionType": "grounded",
            "bucket": "ultra-rare",
            "level": "38-41",
            "weight": 3.6,
            "condition": {
                "biomes": [
                    "#cobblemon:is_mountain"
                ]
            }
        }
    ]
}