{
    "enabled": "true",
    "neededInstalledMods": [],
    "neededUninstalledMods": [],
    "spawns": [
     
				        {
            "id": "runerigus-end-1",
            "pokemon": "runerigus",
            "type": "pokemon",
            "context": "grounded",
            "bucket": "uncommon",
            "level": "60-86",
            "weight": 5.0,
            "condition": {
                "biomes": [
                    "nullscape:void_barrens"
                ]
            }
        }
    ]
}